nsg_octopart/__init__.py
nsg_octopart/nexarClient.py
nsg_octopart/nsgSearch.py
nsg_octopart-0.1.0.dist-info/METADATA
nsg_octopart-0.1.0.dist-info/WHEEL
nsg_octopart-0.1.0.dist-info/RECORD
