Metadata-Version: 2.1
Name: nsg-octopart
Version: 0.1.0
Summary: NSG class for making request to Octopart using nexarClient
Author: Antonio Arroyave
Author-email: antonio.arroyave@nsg-engineering.com
Requires-Python: >=3.10,<4.0
Classifier: Programming Language :: Python :: 3
Classifier: Programming Language :: Python :: 3.10
Classifier: Programming Language :: Python :: 3.11
Requires-Dist: requests (>=2.28.2,<3.0.0)
